COPYING
MANIFEST.in
README.html
README.rst
examplescript.py
gitconfig.sh
install_to_venv.sh
pwman
pwman.cmd
requirements.txt
setup.py
doc/api/libpwman/aes.html
doc/api/libpwman/argon2.html
doc/api/libpwman/cryptsql.html
doc/api/libpwman/database.html
doc/api/libpwman/dbdiff.html
doc/api/libpwman/exception.html
doc/api/libpwman/fileobj.html
doc/api/libpwman/mlock.html
doc/api/libpwman/otp.html
doc/api/libpwman/ui.html
doc/api/libpwman/ui_escape.html
doc/api/libpwman/util.html
doc/api/libpwman/version.html
doc/foreign-licenses/PYTHON-LICENSE.txt
doc/foreign-licenses/README
libpwman/__init__.py
libpwman/__main__.py
libpwman/aes.py
libpwman/argon2.py
libpwman/cryptsql.py
libpwman/database.py
libpwman/dbdiff.py
libpwman/exception.py
libpwman/fileobj.py
libpwman/mlock.py
libpwman/otp.py
libpwman/ui.py
libpwman/ui_escape.py
libpwman/util.py
libpwman/version.py
maintenance/cleantree.sh
maintenance/deb-dependencies-install.sh
maintenance/gen-doc.sh
maintenance/win-install-dependencies.cmd
maintenance/win-standalone-build.cmd
pwman_python.egg-info/PKG-INFO
pwman_python.egg-info/SOURCES.txt
pwman_python.egg-info/dependency_links.txt
pwman_python.egg-info/requires.txt
pwman_python.egg-info/top_level.txt
tests/__init__.py
tests/pwman_tstlib.py
tests/run.sh
tests/test_database_v0.db
tests/test_database_v0.py
tests/test_database_v1.db
tests/test_database_v1.py
tests/test_database_v1_pbkdf2.db
tests/test_escape.py
tests/test_otp.py
tests/test_ui.py