Metadata-Version: 2.4
Name: pwman-python
Version: 2.13
Summary: Commandline password manager
Home-page: https://bues.ch/h/pwman
Author: Michael Büsch
Author-email: m@bues.ch
License: GPL-2.0-or-later
Keywords: password manager command line TOTP 2FA
Classifier: Development Status :: 5 - Production/Stable
Classifier: Environment :: Console
Classifier: Intended Audience :: Developers
Classifier: Intended Audience :: Information Technology
Classifier: Intended Audience :: End Users/Desktop
Classifier: Intended Audience :: System Administrators
Classifier: Operating System :: OS Independent
Classifier: Programming Language :: Python :: 3
Requires-Python: >=3.7
License-File: COPYING
Requires-Dist: argon2-cffi
Requires-Dist: cffi
Requires-Dist: pycryptodomex
Dynamic: author
Dynamic: author-email
Dynamic: classifier
Dynamic: description
Dynamic: description-content-type
Dynamic: home-page
Dynamic: keywords
Dynamic: license
Dynamic: license-file
Dynamic: requires-dist
Dynamic: requires-python
Dynamic: summary
